dora_cli/__init__.py
dora_cli/dora_cli.abi3.so
dora_cli.libs/libgcc_s-262c4f60.so.1
dora_rs_cli-0.4.1.dist-info/METADATA
dora_rs_cli-0.4.1.dist-info/WHEEL
dora_rs_cli-0.4.1.dist-info/entry_points.txt
dora_rs_cli-0.4.1.dist-info/RECORD
