Metadata-Version: 2.4
Name: dora-rs-cli
Version: 0.4.1
Requires-Dist: dora-rs>=0.3.9
Requires-Dist: uv
License: MIT
Requires-Python: >=3.8
